nsist/__init__.py
nsist/__main__.py
nsist/_system_path.py
nsist/commands.py
nsist/configreader.py
nsist/copymodules.py
nsist/glossyorb.ico
nsist/nsiswriter.py
nsist/pyapp.nsi
nsist/pyapp_msvcrt.nsi
nsist/util.py
nsist/wheels.py
nsist/msvcrt/x64/api-ms-win-core-console-l1-1-0.dll
nsist/msvcrt/x64/api-ms-win-core-datetime-l1-1-0.dll
nsist/msvcrt/x64/api-ms-win-core-debug-l1-1-0.dll
nsist/msvcrt/x64/api-ms-win-core-errorhandling-l1-1-0.dll
nsist/msvcrt/x64/api-ms-win-core-file-l1-1-0.dll
nsist/msvcrt/x64/api-ms-win-core-file-l1-2-0.dll
nsist/msvcrt/x64/api-ms-win-core-file-l2-1-0.dll
nsist/msvcrt/x64/api-ms-win-core-handle-l1-1-0.dll
nsist/msvcrt/x64/api-ms-win-core-heap-l1-1-0.dll
nsist/msvcrt/x64/api-ms-win-core-interlocked-l1-1-0.dll
nsist/msvcrt/x64/api-ms-win-core-libraryloader-l1-1-0.dll
nsist/msvcrt/x64/api-ms-win-core-localization-l1-2-0.dll
nsist/msvcrt/x64/api-ms-win-core-memory-l1-1-0.dll
nsist/msvcrt/x64/api-ms-win-core-namedpipe-l1-1-0.dll
nsist/msvcrt/x64/api-ms-win-core-processenvironment-l1-1-0.dll
nsist/msvcrt/x64/api-ms-win-core-processthreads-l1-1-0.dll
nsist/msvcrt/x64/api-ms-win-core-processthreads-l1-1-1.dll
nsist/msvcrt/x64/api-ms-win-core-profile-l1-1-0.dll
nsist/msvcrt/x64/api-ms-win-core-rtlsupport-l1-1-0.dll
nsist/msvcrt/x64/api-ms-win-core-string-l1-1-0.dll
nsist/msvcrt/x64/api-ms-win-core-synch-l1-1-0.dll
nsist/msvcrt/x64/api-ms-win-core-synch-l1-2-0.dll
nsist/msvcrt/x64/api-ms-win-core-sysinfo-l1-1-0.dll
nsist/msvcrt/x64/api-ms-win-core-timezone-l1-1-0.dll
nsist/msvcrt/x64/api-ms-win-core-util-l1-1-0.dll
nsist/msvcrt/x64/api-ms-win-crt-conio-l1-1-0.dll
nsist/msvcrt/x64/api-ms-win-crt-convert-l1-1-0.dll
nsist/msvcrt/x64/api-ms-win-crt-environment-l1-1-0.dll
nsist/msvcrt/x64/api-ms-win-crt-filesystem-l1-1-0.dll
nsist/msvcrt/x64/api-ms-win-crt-heap-l1-1-0.dll
nsist/msvcrt/x64/api-ms-win-crt-locale-l1-1-0.dll
nsist/msvcrt/x64/api-ms-win-crt-math-l1-1-0.dll
nsist/msvcrt/x64/api-ms-win-crt-multibyte-l1-1-0.dll
pynsistfix-2.8.post1.dist-info/entry_points.txt
pynsistfix-2.8.post1.dist-info/WHEEL
pynsistfix-2.8.post1.dist-info/METADATA
pynsistfix-2.8.post1.dist-info/RECORD
