Metadata-Version: 2.1
Name: pynsistfix
Version: 2.8.post1
Summary: Build NSIS installers for Python applications.
Author-email: Thomas Kluyver <thomas@kluyver.me.uk>
Requires-Python: >=3.6
Classifier: License :: OSI Approved :: MIT License
Classifier: Intended Audience :: Developers
Classifier: Environment :: Win32 (MS Windows)
Classifier: Programming Language :: Python :: 3
Classifier: Topic :: Software Development
Classifier: Topic :: System :: Installation/Setup
Classifier: Topic :: System :: Software Distribution
Requires-Dist: requests
Requires-Dist: requests_download
Requires-Dist: jinja2
Requires-Dist: yarg
Requires-Dist: distlib >=0.3
Requires-Dist: testpath ; extra == "test"
Requires-Dist: responses ; extra == "test"
Project-URL: Documentation, https://pynsist.readthedocs.io/en/latest/
Project-URL: Home, https://github.com/embykeeper/pynsist-fix
Project-URL: Source, https://github.com/takluyver/pynsist
Provides-Extra: test
